{
  "sorted_middleware": [],
  "middleware": {
    "/": {
      "files": [
        "server/edge/chunks/_4d0e78e7._.js",
        "server/edge/chunks/[root-of-the-server]__eff7c29f._.js",
        "server/edge/chunks/turbopack-mobilin_edge-wrapper_a5766179.js"
      ],
      "name": "middleware",
      "page": "/",
      "matchers": [
        {
          "regexp": "/:nextData(_next/data/[^/]{1,})?/((?!api|_next/static|_next/image|images|favicon.ico|.*\\.png$).*){(\\\\.json)}?",
          "originalSource": "/((?!api|_next/static|_next/image|images|favicon.ico|.*\\.png$).*)"
        }
      ],
      "wasm": [],
      "assets": [],
      "env": {
        "__NEXT_BUILD_ID": "development",
        "NEXT_SERVER_ACTIONS_ENCRYPTION_KEY": "uVRwObCeIrnN/spTkRF6vKZasm2mnRFpCcqEQpwwm04=",
        "__NEXT_PREVIEW_MODE_ID": "59ae2ed853063b7972e9938a2571173e",
        "__NEXT_PREVIEW_MODE_ENCRYPTION_KEY": "820a09af5957e2f5bb8c70e23d33fb620308bc08cadd4c097a92f2499b14b1bb",
        "__NEXT_PREVIEW_MODE_SIGNING_KEY": "8755765c3287637343c9e0615b08b8706e991e62d3b38fdcf91df16c6d648985"
      }
    }
  },
  "instrumentation": null,
  "functions": {}
}